boltlight/__init__.py
boltlight/blink.py
boltlight/boltlight.proto
boltlight/boltlight.py
boltlight/boltlight_pb2.py
boltlight/boltlight_pb2_grpc.py
boltlight/db.py
boltlight/errors.py
boltlight/light_clightning.py
boltlight/light_eclair.py
boltlight/light_electrum.py
boltlight/light_lnd.py
boltlight/macaroons.py
boltlight/migrate.py
boltlight/migrations/README
boltlight/migrations/__init__.py
boltlight/migrations/alembic.ini
boltlight/migrations/env.py
boltlight/migrations/script.py.mako
boltlight/migrations/versions/__init__.py
boltlight/pairing.py
boltlight/secure.py
boltlight/settings.py
boltlight/share/boltlight.service
boltlight/share/complete-blink.bash
boltlight/share/complete-blink.zsh
boltlight/share/config.sample
boltlight/utils/__init__.py
boltlight/utils/bitcoin.py
boltlight/utils/boltlight.py
boltlight/utils/db.py
boltlight/utils/exceptions.py
boltlight/utils/misc.py
boltlight/utils/network.py
boltlight/utils/security.py
boltlight-2.1.0.dist-info/entry_points.txt
boltlight-2.1.0.dist-info/COPYING
boltlight-2.1.0.dist-info/WHEEL
boltlight-2.1.0.dist-info/METADATA
boltlight-2.1.0.dist-info/RECORD
