Metadata-Version: 2.1
Name: boltlight
Version: 2.1.0
Summary: Lightning Network node wrapper
Home-page: https://hashbeam.gitlab.io/boltlight
License: AGPL-3.0-or-later
Keywords: lightning network,node,wrapper,bitcoin
Author: Hashbeam
Author-email: hashbeam@protonmail.com
Requires-Python: >=3.9.0,<4.0.0
Classifier: Development Status :: 4 - Beta
Classifier: Intended Audience :: Developers
Classifier: License :: OSI Approved :: GNU Affero General Public License v3 or later (AGPLv3+)
Classifier: Natural Language :: English
Classifier: Operating System :: MacOS
Classifier: Operating System :: POSIX :: Linux
Classifier: Programming Language :: Python :: 3
Classifier: Programming Language :: Python :: 3.10
Classifier: Programming Language :: Python :: 3.9
Classifier: Topic :: Other/Nonlisted Topic
Requires-Dist: alembic (>=1.5.5,<2.0.0)
Requires-Dist: click (>=8.0.4,<9.0.0)
Requires-Dist: googleapis-common-protos (>=1.53.0,<2.0.0)
Requires-Dist: grpcio (>=1.43.0,<2.0.0)
Requires-Dist: lnd-proto (==0.13.3-beta.0)
Requires-Dist: macaroonbakery (>=1.3.1,<2.0.0)
Requires-Dist: protobuf (>=3.19.1,<4.0.0)
Requires-Dist: pylibscrypt (>=1.8.0,<2.0.0)
Requires-Dist: pyln-client (==0.10.1)
Requires-Dist: pymacaroons (>=0.13.0,<0.14.0)
Requires-Dist: pynacl (>=1.3.0,<2.0.0)
Requires-Dist: qrcode (>=6.1,<7.0)
Requires-Dist: requests (>=2.25.1,<3.0.0)
Requires-Dist: sqlalchemy (>=1.3.23,<1.4.0)
Project-URL: Documentation, https://hashbeam.gitlab.io/boltlight-doc
Project-URL: Repository, https://gitlab.com/hashbeam/boltlight
